{"assets":{"AB5EFCA9F13D89F4D237B189B9C45E5D":{"type":"texture","index":1,"assetRequest":{"type":"slide","state":"contents","slide":"none"},"url":{"native":"assets\/1CCC881A-9C80-4EDB-AF2B-7C4DD3A33C42.pdf"},"width":373,"height":308},"C637428BEDA8EA5521BD7B7DD6AD564A":{"type":"texture","index":6,"assetRequest":{"type":"slide","state":"contents","slide":"none"},"url":{"native":"assets\/1CCC881A-9C80-4EDB-AF2B-7C4DD3A33C42.pdf"},"width":787,"height":678},"4D26B0818E282613016CC2F8132B36B3":{"type":"texture","index":5,"assetRequest":{"type":"slide","state":"contents","slide":"none"},"url":{"native":"assets\/1CCC881A-9C80-4EDB-AF2B-7C4DD3A33C42.pdf"},"width":373,"height":308},"FB85E88F38938EB5329DD8B4AEE81A55":{"type":"texture","index":4,"assetRequest":{"type":"slide","state":"contents","slide":"none"},"url":{"native":"assets\/1CCC881A-9C80-4EDB-AF2B-7C4DD3A33C42.pdf"},"width":787,"height":677},"63D6FC2C8E93EA0520B2F688B5D05579":{"type":"texture","index":0,"assetRequest":{"type":"slide","state":"contents","slide":"none"},"url":{"native":"assets\/1CCC881A-9C80-4EDB-AF2B-7C4DD3A33C42.pdf"},"width":1920,"height":1080},"C067D457C4B0CAF7DBE6D52A086699E5":{"type":"texture","index":3,"assetRequest":{"type":"slide","state":"contents","slide":"none"},"url":{"native":"assets\/1CCC881A-9C80-4EDB-AF2B-7C4DD3A33C42.pdf"},"width":1348,"height":268},"003DAF0C715AF540F318F49AF06BC253":{"type":"texture","index":2,"assetRequest":{"type":"slide","state":"contents","slide":"none"},"url":{"native":"assets\/1CCC881A-9C80-4EDB-AF2B-7C4DD3A33C42.pdf"},"width":375,"height":308}},"events":[{"effects":[{"beginTime":0,"baseLayer":{"animations":[],"initialState":{"affineTransform":[1,0,0,1,0,0],"masksToBounds":false,"rotation":0,"scale":1,"position":{"pointX":960,"pointY":540},"width":1920,"sublayerTransform":[1,0,0,0,0,1,0,0,0,0,1,0,0,0,0,1],"contentsRect":{"y":0,"x":0,"width":1,"height":1},"opacity":1,"edgeAntialiasingMask":251658240,"height":1080,"hidden":false,"anchorPoint":{"pointX":0.5,"pointY":0.5}},"objectID":"0","layers":[{"animations":[],"initialState":{"affineTransform":[1,0,0,1,0,0],"masksToBounds":false,"rotation":0,"scale":1,"position":{"pointX":960,"pointY":540},"width":1920,"sublayerTransform":[1,0,0,0,0,1,0,0,0,0,1,-0.00035007912466775983,0,0,0,1],"contentsRect":{"y":0,"x":0,"width":1,"height":1},"opacity":1,"edgeAntialiasingMask":251658240,"height":1080,"hidden":false,"anchorPoint":{"pointX":0.5,"pointY":0.5}},"layers":[{"animations":[{"timeOffset":0,"beginTime":0,"repeatCount":0,"animations":[{"timeOffset":0,"from":{"scalar":0},"beginTime":0,"repeatCount":0,"fillMode":"both","duration":1,"autoreverses":false,"timingFunction":"EaseInEaseOut","property":"zPosition","to":{"scalar":0}}],"fillMode":"both","autoreverses":false,"duration":1}],"initialState":{"affineTransform":[1,0,0,1,0,0],"masksToBounds":false,"rotation":0,"scale":1,"position":{"pointX":960,"pointY":540},"width":1920,"sublayerTransform":[1,0,0,0,0,1,0,0,0,0,1,0,0,0,0,1],"contentsRect":{"y":0,"x":0,"width":1,"height":1},"opacity":1,"edgeAntialiasingMask":251658240,"height":1080,"hidden":false,"anchorPoint":{"pointX":0.5,"pointY":0.5}},"layers":[{"animations":[],"layers":[],"texturedRectangle":{"isBackgroundTexture":true,"singleTextureOpacity":1,"textureType":1,"textBaseline":0,"textXHeight":0,"isVerticalText":false},"initialState":{"affineTransform":[1,0,0,1,0,0],"masksToBounds":false,"rotation":0,"scale":1,"position":{"pointX":960,"pointY":540},"width":1920,"sublayerTransform":[1,0,0,0,0,1,0,0,0,0,1,0,0,0,0,1],"contentsRect":{"y":0,"x":0,"width":1,"height":1},"opacity":1,"edgeAntialiasingMask":0,"height":1080,"hidden":false,"anchorPoint":{"pointX":0.5,"pointY":0.5}},"texture":"63D6FC2C8E93EA0520B2F688B5D05579"}]}]},{"animations":[{"timeOffset":0,"beginTime":0,"repeatCount":0,"animations":[{"timeOffset":0,"from":{"scalar":0.001},"beginTime":0,"repeatCount":0,"fillMode":"both","duration":1,"autoreverses":false,"timingFunction":"EaseInEaseOut","property":"zPosition","to":{"scalar":0.001}}],"fillMode":"both","autoreverses":false,"duration":1}],"initialState":{"affineTransform":[1,0,0,1,0,0],"masksToBounds":false,"rotation":0,"scale":1,"position":{"pointX":1123.3014068603516,"pointY":271.84857177734375},"width":363.95413208007812,"sublayerTransform":[1,0,0,0,0,1,0,0,0,0,1,0,0,0,0,1],"contentsRect":{"y":0,"x":0,"width":1,"height":1},"opacity":1,"edgeAntialiasingMask":251658240,"height":305.52706909179688,"hidden":false,"anchorPoint":{"pointX":0.5,"pointY":0.5}},"layers":[{"animations":[{"timeOffset":0,"beginTime":0,"repeatCount":0,"animations":[{"timeOffset":0,"from":{"texture":"AB5EFCA9F13D89F4D237B189B9C45E5D"},"beginTime":0,"repeatCount":0,"fillMode":"both","duration":1,"autoreverses":false,"timingFunction":"EaseInEaseOut","property":"contents","to":{"texture":"4D26B0818E282613016CC2F8132B36B3"}},{"timeOffset":0,"from":{"pointX":0,"pointY":0},"beginTime":0,"repeatCount":0,"fillMode":"both","duration":1,"autoreverses":false,"timingFunction":"EaseInEaseOut","property":"transform.translation","to":{"pointX":584,"pointY":-2}}],"fillMode":"both","autoreverses":false,"duration":1}],"layers":[],"texturedRectangle":{"isBackgroundTexture":true,"singleTextureOpacity":1,"textureType":5,"textBaseline":0,"textXHeight":0,"isVerticalText":false},"initialState":{"affineTransform":[1,0,0,1,0,0],"masksToBounds":false,"rotation":0,"scale":1,"position":{"pointX":181.97706985473636,"pointY":152.76353454589844},"width":373,"sublayerTransform":[1,0,0,0,0,1,0,0,0,0,1,0,0,0,0,1],"contentsRect":{"y":0,"x":0,"width":1,"height":1},"opacity":1,"edgeAntialiasingMask":0,"height":308,"hidden":false,"anchorPoint":{"pointX":0.50751048438350899,"pointY":0.49950834992644072}},"texture":"AB5EFCA9F13D89F4D237B189B9C45E5D"}]},{"animations":[{"timeOffset":0,"beginTime":0,"repeatCount":0,"animations":[{"timeOffset":0,"from":{"scalar":0.002},"beginTime":0,"repeatCount":0,"fillMode":"both","duration":1,"autoreverses":false,"timingFunction":"EaseInEaseOut","property":"zPosition","to":{"scalar":0.002}}],"fillMode":"both","autoreverses":false,"duration":1}],"initialState":{"affineTransform":[1,0,0,1,0,0],"masksToBounds":false,"rotation":0,"scale":1,"position":{"pointX":700.44297790527344,"pointY":1250.9523773193359},"width":365.79672241210938,"sublayerTransform":[1,0,0,0,0,1,0,0,0,0,1,0,0,0,0,1],"contentsRect":{"y":0,"x":0,"width":1,"height":1},"opacity":1,"edgeAntialiasingMask":251658240,"height":305.52706909179688,"hidden":false,"anchorPoint":{"pointX":0.5,"pointY":0.5}},"layers":[{"animations":[{"timeOffset":0,"beginTime":0,"repeatCount":0,"animations":[{"timeOffset":0,"from":{"scalar":0},"beginTime":0.66670000000000007,"repeatCount":0,"fillMode":"both","duration":0.33329999999999999,"autoreverses":false,"timingFunction":"EaseInEaseOut","property":"opacity","to":{"scalar":1}},{"timeOffset":0,"from":{"scalar":false},"beginTime":0.66670000000000007,"repeatCount":0,"fillMode":"forwards","property":"hidden","autoreverses":false,"duration":0.33329999999999993,"to":{"scalar":false}}],"fillMode":"both","autoreverses":false,"duration":1}],"layers":[],"texturedRectangle":{"isBackgroundTexture":true,"singleTextureOpacity":1,"textureType":5,"textBaseline":0,"textXHeight":0,"isVerticalText":false},"initialState":{"affineTransform":[1,0,0,1,0,0],"masksToBounds":false,"rotation":0,"scale":1,"position":{"pointX":182.89836502075195,"pointY":152.76353454589844},"width":375,"sublayerTransform":[1,0,0,0,0,1,0,0,0,0,1,0,0,0,0,1],"contentsRect":{"y":0,"x":0,"width":1,"height":1},"opacity":1,"edgeAntialiasingMask":0,"height":308,"hidden":true,"anchorPoint":{"pointX":0.50784795125325521,"pointY":0.49984538090693487}},"texture":"003DAF0C715AF540F318F49AF06BC253"}]},{"animations":[{"timeOffset":0,"beginTime":0,"repeatCount":0,"animations":[{"timeOffset":0,"from":{"scalar":0.0030000000000000001},"beginTime":0,"repeatCount":0,"fillMode":"both","duration":1,"autoreverses":false,"timingFunction":"EaseInEaseOut","property":"zPosition","to":{"scalar":0.0030000000000000001}}],"fillMode":"both","autoreverses":false,"duration":1}],"initialState":{"affineTransform":[1,0,0,1,0,0],"masksToBounds":false,"rotation":0,"scale":1,"position":{"pointX":681.75678443908691,"pointY":1084.2367553710938},"width":1345.480712890625,"sublayerTransform":[1,0,0,0,0,1,0,0,0,0,1,0,0,0,0,1],"contentsRect":{"y":0,"x":0,"width":1,"height":1},"opacity":1,"edgeAntialiasingMask":251658240,"height":264.08898925781239,"hidden":false,"anchorPoint":{"pointX":0.5,"pointY":0.5}},"layers":[{"animations":[{"timeOffset":0,"beginTime":0,"repeatCount":0,"animations":[{"timeOffset":0,"from":{"scalar":0},"beginTime":0.66670000000000007,"repeatCount":0,"fillMode":"both","duration":0.33329999999999999,"autoreverses":false,"timingFunction":"EaseInEaseOut","property":"opacity","to":{"scalar":1}},{"timeOffset":0,"from":{"scalar":false},"beginTime":0.66670000000000007,"repeatCount":0,"fillMode":"forwards","property":"hidden","autoreverses":false,"duration":0.33329999999999993,"to":{"scalar":false}}],"fillMode":"both","autoreverses":false,"duration":1}],"layers":[],"texturedRectangle":{"singleTextureOpacity":1,"textXHeight":0,"shapePath":{"lineWidth":1,"flatness":0.59999999999999998,"lineCapStyle":0,"elements":[{"type":"MoveToPoint","points":[[1359.3333649971726,134.5333059603048]]},{"type":"AddLine","points":[[1308.3567987090428,393.65563988134102]]},{"type":"AddLine","points":[[-11.819796118998816,133.94020478188247]]},{"type":"CloseSubpath"},{"type":"MoveToPoint","points":[[1359.3333649971726,134.5333059603048]]}],"windingRule":0,"lineJoinStyle":0,"miterLimit":10},"isBackgroundTexture":true,"textBaseline":0,"isVerticalText":false,"textureType":5},"initialState":{"affineTransform":[0.9811932509918927,0.19302798814669511,-0.19302798814669511,0.9811932509918927,0,0],"masksToBounds":false,"rotation":0.19424724148485448,"scale":1,"position":{"pointX":672.7403564453125,"pointY":132.04449462890611},"width":1348,"sublayerTransform":[1,0,0,0,0,1,0,0,0,0,1,0,0,0,0,1],"contentsRect":{"y":0,"x":0,"width":1,"height":1},"opacity":1,"edgeAntialiasingMask":0,"height":268,"hidden":true,"anchorPoint":{"pointX":0.49981957302602886,"pointY":0.50088341556378213}},"texture":"C067D457C4B0CAF7DBE6D52A086699E5"}]},{"animations":[{"timeOffset":0,"beginTime":0,"repeatCount":0,"animations":[{"timeOffset":0,"from":{"scalar":0.0040000000000000001},"beginTime":0,"repeatCount":0,"fillMode":"both","duration":1,"autoreverses":false,"timingFunction":"EaseInEaseOut","property":"zPosition","to":{"scalar":0.0040000000000000001}}],"fillMode":"both","autoreverses":false,"duration":1}],"initialState":{"affineTransform":[1,0,0,1,0,0],"masksToBounds":false,"rotation":0,"scale":1,"position":{"pointX":996.43304443359375,"pointY":745.58782958984375},"width":784.2451171875,"sublayerTransform":[1,0,0,0,0,1,0,0,0,0,1,0,0,0,0,1],"contentsRect":{"y":0,"x":0,"width":1,"height":1},"opacity":1,"edgeAntialiasingMask":251658240,"height":674.5345458984375,"hidden":false,"anchorPoint":{"pointX":0.5,"pointY":0.5}},"layers":[{"animations":[{"timeOffset":0,"beginTime":0,"repeatCount":0,"animations":[{"timeOffset":0,"from":{"scalar":1},"beginTime":0,"repeatCount":0,"fillMode":"both","duration":1,"autoreverses":false,"timingFunction":"EaseInEaseOut","property":"transform.scale.x","to":{"scalar":1}},{"timeOffset":0,"from":{"scalar":1},"beginTime":0,"repeatCount":0,"fillMode":"both","duration":1,"autoreverses":false,"timingFunction":"EaseInEaseOut","property":"transform.scale.y","to":{"scalar":1.0014771048744462}},{"timeOffset":0,"from":{"texture":"FB85E88F38938EB5329DD8B4AEE81A55"},"beginTime":0.33330000000000004,"repeatCount":0,"fillMode":"both","duration":0.66669999999999996,"autoreverses":false,"timingFunction":"EaseInEaseOut","property":"contents","to":{"texture":"C637428BEDA8EA5521BD7B7DD6AD564A"}},{"timeOffset":0,"from":{"pointX":0,"pointY":0},"beginTime":0,"repeatCount":0,"fillMode":"both","duration":1,"autoreverses":false,"timingFunction":"EaseInEaseOut","property":"transform.translation","to":{"pointX":584,"pointY":-1.4998702664847769}}],"fillMode":"both","autoreverses":false,"duration":1}],"layers":[],"texturedRectangle":{"isBackgroundTexture":true,"singleTextureOpacity":1,"textureType":5,"textBaseline":0,"textXHeight":0,"isVerticalText":false},"initialState":{"affineTransform":[1,0,0,1,0,0],"masksToBounds":false,"rotation":0,"scale":1,"position":{"pointX":392.12257385253906,"pointY":337.26727294921875},"width":787,"sublayerTransform":[1,0,0,0,0,1,0,0,0,0,1,0,0,0,0,1],"contentsRect":{"y":0,"x":0,"width":1,"height":1},"opacity":1,"edgeAntialiasingMask":0,"height":677,"hidden":false,"anchorPoint":{"pointX":0.49991494242996548,"pointY":0.50012973351527878}},"texture":"FB85E88F38938EB5329DD8B4AEE81A55"}]}]},"effects":[],"duration":1,"type":"transition","name":"apple:magic-move-implied-motion-path","objectID":"0"}],"automaticPlay":true,"hyperlinks":[],"accessibility":[{"text":"Swift  iOS","targetRectangle":{"y":135.30636596679688,"x":962.70838928222656,"width":255.58500000000004,"height":66.404617309570312}},{"text":"App Dev.","targetRectangle":{"y":203.30636596679688,"x":962.70838928222656,"width":232.31999999999994,"height":66.404617309570312}}],"baseLayer":{"animations":[],"initialState":{"affineTransform":[1,0,0,1,0,0],"masksToBounds":false,"rotation":0,"scale":1,"position":{"pointX":960,"pointY":540},"width":1920,"sublayerTransform":[1,0,0,0,0,1,0,0,0,0,1,0,0,0,0,1],"contentsRect":{"y":0,"x":0,"width":1,"height":1},"opacity":1,"edgeAntialiasingMask":251658240,"height":1080,"hidden":false,"anchorPoint":{"pointX":0.5,"pointY":0.5}},"objectID":"0","layers":[{"animations":[],"initialState":{"affineTransform":[1,0,0,1,0,0],"masksToBounds":false,"rotation":0,"scale":1,"position":{"pointX":960,"pointY":540},"width":1920,"sublayerTransform":[1,0,0,0,0,1,0,0,0,0,1,-0.00035007912466775983,0,0,0,1],"contentsRect":{"y":0,"x":0,"width":1,"height":1},"opacity":1,"edgeAntialiasingMask":251658240,"height":1080,"hidden":false,"anchorPoint":{"pointX":0.5,"pointY":0.5}},"layers":[{"animations":[],"initialState":{"affineTransform":[1,0,0,1,0,0],"masksToBounds":false,"rotation":0,"scale":1,"position":{"pointX":960,"pointY":540},"width":1920,"sublayerTransform":[1,0,0,0,0,1,0,0,0,0,1,0,0,0,0,1],"contentsRect":{"y":0,"x":0,"width":1,"height":1},"opacity":1,"edgeAntialiasingMask":251658240,"height":1080,"hidden":false,"anchorPoint":{"pointX":0.5,"pointY":0.5}},"layers":[{"animations":[],"layers":[],"texturedRectangle":{"isBackgroundTexture":true,"singleTextureOpacity":1,"textureType":1,"textBaseline":0,"textXHeight":0,"isVerticalText":false},"initialState":{"affineTransform":[1,0,0,1,0,0],"masksToBounds":false,"rotation":0,"scale":1,"position":{"pointX":960,"pointY":540},"width":1920,"sublayerTransform":[1,0,0,0,0,1,0,0,0,0,1,0,0,0,0,1],"contentsRect":{"y":0,"x":0,"width":1,"height":1},"opacity":1,"edgeAntialiasingMask":0,"height":1080,"hidden":false,"anchorPoint":{"pointX":0.5,"pointY":0.5}},"texture":"63D6FC2C8E93EA0520B2F688B5D05579"}]}]},{"animations":[],"initialState":{"affineTransform":[1,0,0,1,0,0],"masksToBounds":false,"rotation":0,"scale":1,"position":{"pointX":1123.3014068603516,"pointY":271.84857177734375},"width":363.95413208007812,"sublayerTransform":[1,0,0,0,0,1,0,0,0,0,1,0,0,0,0,1],"contentsRect":{"y":0,"x":0,"width":1,"height":1},"opacity":1,"edgeAntialiasingMask":251658240,"height":305.52706909179688,"hidden":false,"anchorPoint":{"pointX":0.5,"pointY":0.5}},"layers":[{"animations":[],"layers":[],"texturedRectangle":{"isBackgroundTexture":true,"singleTextureOpacity":1,"textureType":5,"textBaseline":0,"textXHeight":0,"isVerticalText":false},"initialState":{"affineTransform":[1,0,0,1,0,0],"masksToBounds":false,"rotation":0,"scale":1,"position":{"pointX":181.97706985473636,"pointY":152.76353454589844},"width":373,"sublayerTransform":[1,0,0,0,0,1,0,0,0,0,1,0,0,0,0,1],"contentsRect":{"y":0,"x":0,"width":1,"height":1},"opacity":1,"edgeAntialiasingMask":0,"height":308,"hidden":false,"anchorPoint":{"pointX":0.50751048438350899,"pointY":0.49950834992644072}},"texture":"AB5EFCA9F13D89F4D237B189B9C45E5D"}]},{"animations":[],"initialState":{"affineTransform":[1,0,0,1,0,0],"masksToBounds":false,"rotation":0,"scale":1,"position":{"pointX":700.44297790527344,"pointY":1250.9523773193359},"width":365.79672241210938,"sublayerTransform":[1,0,0,0,0,1,0,0,0,0,1,0,0,0,0,1],"contentsRect":{"y":0,"x":0,"width":1,"height":1},"opacity":1,"edgeAntialiasingMask":251658240,"height":305.52706909179688,"hidden":false,"anchorPoint":{"pointX":0.5,"pointY":0.5}},"layers":[{"animations":[],"layers":[],"texturedRectangle":{"isBackgroundTexture":true,"singleTextureOpacity":1,"textureType":5,"textBaseline":0,"textXHeight":0,"isVerticalText":false},"initialState":{"affineTransform":[1,0,0,1,0,0],"masksToBounds":false,"rotation":0,"scale":1,"position":{"pointX":182.89836502075195,"pointY":152.76353454589844},"width":375,"sublayerTransform":[1,0,0,0,0,1,0,0,0,0,1,0,0,0,0,1],"contentsRect":{"y":0,"x":0,"width":1,"height":1},"opacity":1,"edgeAntialiasingMask":0,"height":308,"hidden":true,"anchorPoint":{"pointX":0.50784795125325521,"pointY":0.49984538090693487}},"texture":"003DAF0C715AF540F318F49AF06BC253"}]},{"animations":[],"initialState":{"affineTransform":[1,0,0,1,0,0],"masksToBounds":false,"rotation":0,"scale":1,"position":{"pointX":681.75678443908691,"pointY":1084.2367553710938},"width":1345.480712890625,"sublayerTransform":[1,0,0,0,0,1,0,0,0,0,1,0,0,0,0,1],"contentsRect":{"y":0,"x":0,"width":1,"height":1},"opacity":1,"edgeAntialiasingMask":251658240,"height":264.08898925781239,"hidden":false,"anchorPoint":{"pointX":0.5,"pointY":0.5}},"layers":[{"animations":[],"layers":[],"texturedRectangle":{"singleTextureOpacity":1,"textXHeight":0,"shapePath":{"lineWidth":1,"flatness":0.59999999999999998,"lineCapStyle":0,"elements":[{"type":"MoveToPoint","points":[[1359.3333649971726,134.5333059603048]]},{"type":"AddLine","points":[[1308.3567987090428,393.65563988134102]]},{"type":"AddLine","points":[[-11.819796118998816,133.94020478188247]]},{"type":"CloseSubpath"},{"type":"MoveToPoint","points":[[1359.3333649971726,134.5333059603048]]}],"windingRule":0,"lineJoinStyle":0,"miterLimit":10},"isBackgroundTexture":true,"textBaseline":0,"isVerticalText":false,"textureType":5},"initialState":{"affineTransform":[0.9811932509918927,0.19302798814669511,-0.19302798814669511,0.9811932509918927,0,0],"masksToBounds":false,"rotation":0.19424724148485448,"scale":1,"position":{"pointX":672.7403564453125,"pointY":132.04449462890611},"width":1348,"sublayerTransform":[1,0,0,0,0,1,0,0,0,0,1,0,0,0,0,1],"contentsRect":{"y":0,"x":0,"width":1,"height":1},"opacity":1,"edgeAntialiasingMask":0,"height":268,"hidden":true,"anchorPoint":{"pointX":0.49981957302602886,"pointY":0.50088341556378213}},"texture":"C067D457C4B0CAF7DBE6D52A086699E5"}]},{"animations":[],"initialState":{"affineTransform":[1,0,0,1,0,0],"masksToBounds":false,"rotation":0,"scale":1,"position":{"pointX":996.43304443359375,"pointY":745.58782958984375},"width":784.2451171875,"sublayerTransform":[1,0,0,0,0,1,0,0,0,0,1,0,0,0,0,1],"contentsRect":{"y":0,"x":0,"width":1,"height":1},"opacity":1,"edgeAntialiasingMask":251658240,"height":674.5345458984375,"hidden":false,"anchorPoint":{"pointX":0.5,"pointY":0.5}},"layers":[{"animations":[],"layers":[],"texturedRectangle":{"isBackgroundTexture":true,"singleTextureOpacity":1,"textureType":5,"textBaseline":0,"textXHeight":0,"isVerticalText":false},"initialState":{"affineTransform":[1,0,0,1,0,0],"masksToBounds":false,"rotation":0,"scale":1,"position":{"pointX":392.12257385253906,"pointY":337.26727294921875},"width":787,"sublayerTransform":[1,0,0,0,0,1,0,0,0,0,1,0,0,0,0,1],"contentsRect":{"y":0,"x":0,"width":1,"height":1},"opacity":1,"edgeAntialiasingMask":0,"height":677,"hidden":false,"anchorPoint":{"pointX":0.49991494242996548,"pointY":0.50012973351527878}},"texture":"FB85E88F38938EB5329DD8B4AEE81A55"}]}]}}]}